musa_develop/.utils.py.swp
musa_develop/README.md
musa_develop/__init__.py
musa_develop/auto_gen.py
musa_develop/main.py
musa_develop/utils.py
musa_develop/__pycache__/__init__.cpython-38.pyc
musa_develop/__pycache__/main.cpython-38.pyc
musa_develop/__pycache__/utils.cpython-38.pyc
musa_develop/ansible/.main.py.swp
musa_develop/ansible/__init__.py
musa_develop/ansible/inventory_examples.yaml
musa_develop/ansible/main.py
musa_develop/ansible/__pycache__/__init__.cpython-38.pyc
musa_develop/ansible/__pycache__/main.cpython-38.pyc
musa_develop/ansible/playbook/.playbook.yaml.swp
musa_develop/ansible/playbook/init_docker_swarm_playbook.yaml
musa_develop/ansible/playbook/playbook.yaml
musa_develop/ansible/playbook/playbook_template.yaml
musa_develop/ansible/playbook/reset_docker_swarm_playbook.yaml
musa_develop/ansible/playbook/start_service_playbook.yaml
musa_develop/ansible/service/stack_template.yaml
musa_develop/ansible/shell/run_deepseek_671b_r1.sh
musa_develop/check/.checker.py.swo
musa_develop/check/.checker.py.swp
musa_develop/check/.diagnoser.py.swn
musa_develop/check/.diagnoser.py.swo
musa_develop/check/.diagnoser.py.swp
musa_develop/check/.shell_executor.py.swp
musa_develop/check/.utils.py.swp
musa_develop/check/README.md
musa_develop/check/__init__.py
musa_develop/check/checker.py
musa_develop/check/diagnoser.py
musa_develop/check/shell_executor.py
musa_develop/check/utils.py
musa_develop/check/__pycache__/__init__.cpython-38.pyc
musa_develop/check/__pycache__/checker.cpython-38.pyc
musa_develop/check/__pycache__/diagnoser.cpython-38.pyc
musa_develop/check/__pycache__/shell_executor.cpython-38.pyc
musa_develop/check/__pycache__/utils.cpython-38.pyc
musa_develop/check/test/test_musa.mu
musa_develop/check/test/test_vllm.py
musa_develop/check/test/torch_demo.py
musa_develop/check/test/torch_musa_demo.py
musa_develop/check/test/torchaudio_demo.py
musa_develop/check/test/torchvision_demo.py
musa_develop/check/test/vllm_demo.py
musa_develop-0.4.1.dist-info/METADATA
musa_develop-0.4.1.dist-info/WHEEL
musa_develop-0.4.1.dist-info/entry_points.txt
musa_develop-0.4.1.dist-info/top_level.txt
musa_develop-0.4.1.dist-info/RECORD
